cog_layers/__init__.py
cog_layers/reader/__init__.py
cog_layers/reader/cog.py
cog_layers/reader/io.py
cog_layers/reader/tiler.py
cog_layers/reader/types.py
cog_layers-0.1.0.dist-info/LICENSE
cog_layers-0.1.0.dist-info/METADATA
cog_layers-0.1.0.dist-info/WHEEL
cog_layers-0.1.0.dist-info/RECORD
